cqgridfinity/__init__.py
cqgridfinity/constants.py
cqgridfinity/gf_baseplate.py
cqgridfinity/gf_box.py
cqgridfinity/gf_drawer.py
cqgridfinity/gf_helpers.py
cqgridfinity/gf_obj.py
cqgridfinity/gf_ruggedbox.py
cqgridfinity/scripts/__init__.py
cqgridfinity/scripts/gridfinitybase.py
cqgridfinity/scripts/gridfinitybox.py
cqgridfinity/scripts/ruggedbox.py
cqgridfinity-0.5.7.dist-info/LICENSE
cqgridfinity-0.5.7.dist-info/METADATA
cqgridfinity-0.5.7.dist-info/WHEEL
cqgridfinity-0.5.7.dist-info/entry_points.txt
cqgridfinity-0.5.7.dist-info/top_level.txt
cqgridfinity-0.5.7.dist-info/RECORD
