Metadata-Version: 2.1
Name: cqgridfinity
Version: 0.5.7
Summary: A python library to make Gridfinity compatible objects with CadQuery.
Home-page: https://github.com/michaelgale/cq-gridfinity
Author: Michael Gale
Author-email: michael@fxbricks.com
License: MIT
Classifier: Development Status :: 4 - Beta
Classifier: Natural Language :: English
Classifier: Operating System :: OS Independent
Classifier: Programming Language :: Python :: 3.9
Classifier: Intended Audience :: Developers
Classifier: License :: OSI Approved :: MIT License
Requires-Python: >=3.9
License-File: LICENSE
Requires-Dist: cadquery
Requires-Dist: cqkit>=0.5.6
